medconb_client.py
medconb_client-0.0.4.dist-info/licenses/LICENSE
medconb_client-0.0.4.dist-info/METADATA
medconb_client-0.0.4.dist-info/WHEEL
medconb_client-0.0.4.dist-info/top_level.txt
medconb_client-0.0.4.dist-info/RECORD
