Metadata-Version: 2.4
Name: medconb-client
Version: 0.0.4
Summary: medconb-client is a Python client for the MedConB API.
Author-email: Alexander Vowinkel <alexander.vowinkel@gmail.com>
License-Expression: MIT
Keywords: medconb,client,api,python
Classifier: Programming Language :: Python :: 3
Classifier: Operating System :: OS Independent
Requires-Python: >=3.9
License-File: LICENSE
Requires-Dist: pandas
Requires-Dist: pydantic
Requires-Dist: aiohttp
Requires-Dist: gql
Requires-Dist: requests_toolbelt
Dynamic: license-file
